<annotation><filename>00393.jpg</filename><folder>aug21_seq1_bldg400</folder><source><sourceImage>The MIT-CSAIL database of objects and scenes</sourceImage><sourceAnnotation>The MIT-CSAIL database of objects and scenes</sourceAnnotation></source><object><name>screenFrontal</name><deleted>0</deleted><verified>1</verified><date>04-Apr-2004 00:46:56</date><polygon><pt><x>99</x><y>2</y></pt><pt><x>102</x><y>48</y></pt><pt><x>154</x><y>48</y></pt><pt><x>156</x><y>0</y></pt></polygon><viewpoint><azimuth>270</azimuth></viewpoint></object></annotation>