<annotation><filename>p1010768.jpg</filename><folder>oct28_static_msu</folder><source><sourceImage>The MIT-CSAIL database of objects and scenes</sourceImage><sourceAnnotation>The MIT-CSAIL database of objects and scenes</sourceAnnotation></source><object><name>screenFrontal</name><deleted>0</deleted><verified>1</verified><date>05-Feb-2004 20:12:24</date><polygon><pt><x>36</x><y>27</y></pt><pt><x>40</x><y>71</y></pt><pt><x>68</x><y>72</y></pt><pt><x>95</x><y>69</y></pt><pt><x>94</x><y>24</y></pt></polygon><viewpoint><azimuth>270</azimuth></viewpoint></object></annotation>