<annotation><filename>p1010800.jpg</filename><folder>nov25_static_office</folder><source><sourceImage>The MIT-CSAIL database of objects and scenes</sourceImage><sourceAnnotation>The MIT-CSAIL database of objects and scenes</sourceAnnotation></source><object><name>screenFrontal</name><deleted>0</deleted><verified>1</verified><date>05-Feb-2004 20:07:16</date><polygon><pt><x>61</x><y>47</y></pt><pt><x>61</x><y>48</y></pt><pt><x>63</x><y>90</y></pt><pt><x>73</x><y>91</y></pt><pt><x>73</x><y>92</y></pt><pt><x>74</x><y>93</y></pt><pt><x>103</x><y>92</y></pt><pt><x>103</x><y>89</y></pt><pt><x>113</x><y>88</y></pt><pt><x>112</x><y>45</y></pt></polygon><viewpoint><azimuth>270</azimuth></viewpoint></object></annotation>