<annotation><filename>p1010049.jpg</filename><folder>stata_april_static_office</folder><source><sourceImage>The MIT-CSAIL database of objects and scenes</sourceImage><sourceAnnotation>The MIT-CSAIL database of objects and scenes</sourceAnnotation></source><object><name>screenFrontal</name><deleted>0</deleted><verified>1</verified><date>20-Apr-2004 04:58:48</date><polygon><pt><x>141</x><y>105</y></pt><pt><x>144</x><y>151</y></pt><pt><x>197</x><y>149</y></pt><pt><x>200</x><y>147</y></pt><pt><x>197</x><y>103</y></pt></polygon></object><object><name>screenFrontal</name><deleted>0</deleted><verified>0</verified><date>12-Jul-2005 22:31:42</date><polygon><username></username><pt><x>33</x><y>114</y></pt><pt><x>36</x><y>148</y></pt><pt><x>80</x><y>146</y></pt><pt><x>76</x><y>113</y></pt></polygon></object></annotation>